f1_etl/__init__.py
f1_etl/aggregation.py
f1_etl/config.py
f1_etl/encoders.py
f1_etl/encoders_new.py
f1_etl/extraction.py
f1_etl/feature_engineering.py
f1_etl/logging.py
f1_etl/pipeline.py
f1_etl/resampling.py
f1_etl/time_series.py
f1_etl/train/__init__.py
f1_etl/train/data_preparation.py
f1_etl/train/evaluation.py
f1_etl/train/metadata.py
f1_etl/train/model_factory.py
f1_etl/train/training.py
f1_etl-0.7.0.dist-info/METADATA
f1_etl-0.7.0.dist-info/WHEEL
f1_etl-0.7.0.dist-info/RECORD
