Metadata-Version: 2.4
Name: f1-etl
Version: 0.7.0
Summary: This package contains an ETL pipeline for extracting, transforming, and preparing Formula 1 telemetry data for time series classification tasks, specifically designed for safety car prediction and other F1 data science applications.
Author-email: Sean Sica <23294618+seansica@users.noreply.github.com>
Requires-Python: >=3.11
Requires-Dist: aeon
Requires-Dist: fastf1>=3.5.3
Requires-Dist: imbalanced-learn
Requires-Dist: pandas>=2.3.0
Requires-Dist: tqdm>=4.67.1
